queryguard/__init__.py
queryguard/__main__.py
queryguard/cli.py
queryguard/config.py
queryguard/engine.py
queryguard/exceptions.py
queryguard/files.py
queryguard/output.py
queryguard/parser.py
queryguard/rules.py
queryguard-0.5.0.dist-info/LICENSE
queryguard-0.5.0.dist-info/METADATA
queryguard-0.5.0.dist-info/WHEEL
queryguard-0.5.0.dist-info/entry_points.txt
queryguard-0.5.0.dist-info/RECORD
