Metadata-Version: 2.1
Name: QueryGuard
Version: 0.5.0
Summary: A guard against unruly sql.
Author: Tyler Klier
Author-email: tylerklier@gmail.com
Requires-Python: >=3.9,<4.0
Classifier: Programming Language :: Python :: 3
Classifier: Programming Language :: Python :: 3.9
Classifier: Programming Language :: Python :: 3.10
Classifier: Programming Language :: Python :: 3.11
Classifier: Programming Language :: Python :: 3.12
Requires-Dist: rich (>=13.6.0,<14.0.0)
Requires-Dist: sqlparse (>=0.4.4,<0.5.0)
Requires-Dist: tomli (>=2.0.1,<3.0.0) ; python_version < "3.11"
Requires-Dist: typer (>=0.9.0,<0.10.0)
